MANIFEST.in
README.md
setup.py
c/fast_pcst.c
c/fast_pcst.h
c/head_tail_proj.c
c/head_tail_proj.h
c/main_wrapper.c
sparse_learning/__init__.py
sparse_learning/data_process.py
sparse_learning/fast_pcst.py
sparse_learning/file_utils.py
sparse_learning/graph_utils.py
sparse_learning/proj_algo.py
sparse_learning.egg-info/PKG-INFO
sparse_learning.egg-info/SOURCES.txt
sparse_learning.egg-info/dependency_links.txt
sparse_learning.egg-info/requires.txt
sparse_learning.egg-info/top_level.txt