Metadata-Version: 1.1
Name: sparse-learning
Version: 0.2.4
Summary: A wrapper for sparse learning algorithms.
Home-page: https://github.com/baojianzhou/sparse_learning.git
Author: Baojian Zhou
Author-email: bzhou6@albany.edu
License: MIT
Keywords: sparse learning,structure sparsity,head/tail projection
Platform: UNKNOWN
Classifier: Programming Language :: Python :: 2
Classifier: License :: OSI Approved :: MIT License
Classifier: Operating System :: POSIX :: Linux
